mcroute/__init__.py
mcroute/matrix.py
mcroute/mcroute.py
mcroute/vector.py
mcroute-1.1.0.dist-info/LICENSE
mcroute-1.1.0.dist-info/METADATA
mcroute-1.1.0.dist-info/WHEEL
mcroute-1.1.0.dist-info/top_level.txt
mcroute-1.1.0.dist-info/RECORD
