Metadata-Version: 2.1
Name: mcroute
Version: 1.1.0
Summary: Markov chain modelling of transportation networks.
Home-page: https://github.com/wklumpen/mcroute
Author: Willem Klumpenhouwer
Author-email: willem@klumpentown.com
License: UNKNOWN
Platform: UNKNOWN
Classifier: Programming Language :: Python :: 3
Classifier: License :: OSI Approved :: MIT License
Classifier: Operating System :: OS Independent
Classifier: Development Status :: 5 - Production/Stable
Classifier: Intended Audience :: Science/Research
Classifier: Natural Language :: English
Requires-Python: >=3.8
Requires-Dist: decorator
Requires-Dist: networkx
Requires-Dist: numpy
Requires-Dist: scipy
